{
  "jobs": [
    {
      "code": "novice",
      "name": "Novice",
      "next": [
        "swordsman",
        "mage",
        "archer",
        "thief",
        "acolyte",
        "merchant"
      ],
      "statBonus": {
        "str": 0,
        "agi": 0,
        "vit": 0,
        "int": 0,
        "dex": 0,
        "luk": 0
      }
    },
    {
      "code": "swordsman",
      "name": "Swordsman",
      "next": [],
      "statBonus": {
        "str": 2,
        "agi": 0,
        "vit": 2,
        "int": 0,
        "dex": 1,
        "luk": 0
      }
    },
    {
      "code": "mage",
      "name": "Mage",
      "next": [],
      "statBonus": {
        "str": 0,
        "agi": 0,
        "vit": 0,
        "int": 3,
        "dex": 1,
        "luk": 0
      }
    },
    {
      "code": "archer",
      "name": "Archer",
      "next": [],
      "statBonus": {
        "str": 0,
        "agi": 1,
        "vit": 0,
        "int": 0,
        "dex": 3,
        "luk": 0
      }
    },
    {
      "code": "thief",
      "name": "Thief",
      "next": [],
      "statBonus": {
        "str": 1,
        "agi": 3,
        "vit": 0,
        "int": 0,
        "dex": 1
      }
    },
    {
      "code": "acolyte",
      "name": "Acolyte",
      "next": [],
      "statBonus": {
        "str": 0,
        "agi": 0,
        "vit": 1,
        "int": 2,
        "dex": 1,
        "luk": 0
      }
    },
    {
      "code": "merchant",
      "name": "Merchant",
      "next": [],
      "statBonus": {
        "str": 1,
        "agi": 0,
        "vit": 1,
        "int": 0,
        "dex": 1,
        "luk": 1
      }
    }
  ]
}